iot_devices/.mypy_cache/.gitignore
iot_devices/.mypy_cache/3.10/@plugins_snapshot.json
iot_devices/.mypy_cache/3.10/__future__.data.json
iot_devices/.mypy_cache/3.10/__future__.meta.json
iot_devices/.mypy_cache/3.10/_ast.data.json
iot_devices/.mypy_cache/3.10/_ast.meta.json
iot_devices/.mypy_cache/3.10/_codecs.data.json
iot_devices/.mypy_cache/3.10/_codecs.meta.json
iot_devices/.mypy_cache/3.10/_collections_abc.data.json
iot_devices/.mypy_cache/3.10/_collections_abc.meta.json
iot_devices/.mypy_cache/3.10/_ctypes.data.json
iot_devices/.mypy_cache/3.10/_ctypes.meta.json
iot_devices/.mypy_cache/3.10/_decimal.data.json
iot_devices/.mypy_cache/3.10/_decimal.meta.json
iot_devices/.mypy_cache/3.10/_heapq.data.json
iot_devices/.mypy_cache/3.10/_heapq.meta.json
iot_devices/.mypy_cache/3.10/_operator.data.json
iot_devices/.mypy_cache/3.10/_operator.meta.json
iot_devices/.mypy_cache/3.10/_random.data.json
iot_devices/.mypy_cache/3.10/_random.meta.json
iot_devices/.mypy_cache/3.10/_socket.data.json
iot_devices/.mypy_cache/3.10/_socket.meta.json
iot_devices/.mypy_cache/3.10/_thread.data.json
iot_devices/.mypy_cache/3.10/_thread.meta.json
iot_devices/.mypy_cache/3.10/_typeshed/__init__.data.json
iot_devices/.mypy_cache/3.10/_typeshed/__init__.meta.json
iot_devices/.mypy_cache/3.10/_warnings.data.json
iot_devices/.mypy_cache/3.10/_warnings.meta.json
iot_devices/.mypy_cache/3.10/_weakref.data.json
iot_devices/.mypy_cache/3.10/_weakref.meta.json
iot_devices/.mypy_cache/3.10/_weakrefset.data.json
iot_devices/.mypy_cache/3.10/_weakrefset.meta.json
iot_devices/.mypy_cache/3.10/abc.data.json
iot_devices/.mypy_cache/3.10/abc.meta.json
iot_devices/.mypy_cache/3.10/aioesphomeapi/__init__.data.json
iot_devices/.mypy_cache/3.10/aioesphomeapi/__init__.meta.json
iot_devices/.mypy_cache/3.10/aioesphomeapi/_frame_helper/__init__.data.json
iot_devices/.mypy_cache/3.10/aioesphomeapi/_frame_helper/__init__.meta.json
iot_devices/.mypy_cache/3.10/aioesphomeapi/_frame_helper/base.data.json
iot_devices-0.30.1.dist-info/WHEEL
iot_devices-0.30.1.dist-info/entry_points.txt
iot_devices-0.30.1.dist-info/METADATA
iot_devices-0.30.1.dist-info/RECORD
