Metadata-Version: 2.4
Name: iot-devices
Version: 0.30.1
Summary: Framework for creating and using device drives, and a library of devices.
Author: Daniel Dunn
License-Expression: MIT
Requires-Dist: textual
Requires-Dist: scullery>=0.4.0
Requires-Dist: pydantic
Requires-Dist: paho-mqtt
Requires-Dist: yeelight
Requires-Dist: colorzero
Requires-Dist: gpiozero
Requires-Dist: aioesphomeapi==42.7.0
Requires-Dist: websockets
Requires-Dist: niquests
Requires-Dist: uvicorn
Requires-Dist: starlette
Requires-Dist: jsonschema
Requires-Dist: cryptography
Requires-Dist: msgpack
Requires-Dist: msgpack-types
Requires-Dist: aiostream
Requires-Dist: bleak
Requires-Dist: gpsdclient
Requires-Python: >=3.11
